{"noiseKey":{"private":{"type":"Buffer","data":"OMX4FBoqN9SbvODFt9mMhCXVr77Y3qo2kTjELN4Cg14="},"public":{"type":"Buffer","data":"1nMRMdRhBWwL1qHbmwGjgCinEm8dH6KcZlffOmppaGo="}},"pairingEphemeralKeyPair":{"private":{"type":"Buffer","data":"qM3svqZgnpeYSDoo44NgrlazilNJoRj9LIv+9KW+gWA="},"public":{"type":"Buffer","data":"XHrGXYOjp9GCDqZvxYrKFkDo/j+RltRzTbr/PAxksRQ="}},"signedIdentityKey":{"private":{"type":"Buffer","data":"oG6OnE/RZLTZ0dK93mots1fRsw64PkmP8nUlE2I2eFg="},"public":{"type":"Buffer","data":"4hccc+tGAHMQC3bZCBJBrzhmDid3qXaaZ9ptVEu55m4="}},"signedPreKey":{"keyPair":{"private":{"type":"Buffer","data":"aKQTQM2OnRoXaRpY34e0ibVQwBj4id1/nDtFZsbZF28="},"public":{"type":"Buffer","data":"hv2Y5Chy8B/+dpx+f6oJV+CIvh4cAXe6O6EScDPKuAI="}},"signature":{"type":"Buffer","data":"QLl8TT9TYit8qhAFQ2Fq3t+4HyR+DcL11PAhxTNv/w9J55TpgCQkknZrPoGCYjbwR9PHjIsoT4k3EvQ1AguigQ=="},"keyId":1},"registrationId":98,"advSecretKey":"pmJIh8SEx5ifZLTaErickI6G34VLlOyoj/uu36C/HAs=","processedHistoryMessages":[{"key":{"remoteJid":"6283841580448@s.whatsapp.net","fromMe":false,"id":"ACB263A8F2BA317C335AFA68379EDBFE","participant":"","addressingMode":"pn"},"messageTimestamp":1770013838},{"key":{"remoteJid":"6283841580448@s.whatsapp.net","fromMe":false,"id":"AC5D6B79BB7AAF75D849E651C51457A0","participant":"","addressingMode":"pn"},"messageTimestamp":1770013839},{"key":{"remoteJid":"6283841580448@s.whatsapp.net","fromMe":false,"id":"AC6343D286240785B5172A02E01C4E50","participant":"","addressingMode":"pn"},"messageTimestamp":1770013844},{"key":{"remoteJid":"6283841580448@s.whatsapp.net","fromMe":false,"id":"ACEB3E5774031970E5C8990AEC931624","participant":"","addressingMode":"pn"},"messageTimestamp":1770013844},{"key":{"remoteJid":"6283841580448@s.whatsapp.net","fromMe":false,"id":"AC0F1907864D9AA50F721404C9093234","participant":"","addressingMode":"pn"},"messageTimestamp":1770013855},{"key":{"remoteJid":"6283841580448@s.whatsapp.net","fromMe":false,"id":"ACD80BCB691BD992949AA58D3B869612","participant":"","addressingMode":"pn"},"messageTimestamp":1770013865},{"key":{"remoteJid":"6283841580448@s.whatsapp.net","fromMe":false,"id":"ACBFA83D3C202946AF3DB107FF5B84CF","participant":"","addressingMode":"pn"},"messageTimestamp":1770013877},{"key":{"remoteJid":"6283841580448@s.whatsapp.net","fromMe":false,"id":"AC200014F3D4FB43C6E35E69EA7C3083","participant":"","addressingMode":"pn"},"messageTimestamp":1770013888},{"key":{"remoteJid":"6283841580448@s.whatsapp.net","fromMe":false,"id":"AC35AA51277DF4670F64B37498723040","participant":"","addressingMode":"pn"},"messageTimestamp":1770013899},{"key":{"remoteJid":"6283841580448@s.whatsapp.net","fromMe":false,"id":"AC655C0208CF11395FC2C53BD06E3EF1","participant":"","addressingMode":"pn"},"messageTimestamp":1770013910},{"key":{"remoteJid":"6283841580448@s.whatsapp.net","fromMe":false,"id":"AC4E4125EF399A19CD3379686EB1CA10","participant":"","addressingMode":"pn"},"messageTimestamp":1770013914},{"key":{"remoteJid":"6283841580448@s.whatsapp.net","fromMe":false,"id":"ACFE6F7C1302B7DE898EF6ECA2A388BA","participant":"","addressingMode":"pn"},"messageTimestamp":1770013926},{"key":{"remoteJid":"6283841580448@s.whatsapp.net","fromMe":false,"id":"ACCD50E02474E75570EE4C34676AF0E8","participant":"","addressingMode":"pn"},"messageTimestamp":1770013938},{"key":{"remoteJid":"6283841580448@s.whatsapp.net","fromMe":false,"id":"AC79EFD0D93CA58879DFE4E93943D1F6","participant":"","addressingMode":"pn"},"messageTimestamp":1770013975},{"key":{"remoteJid":"6283841580448@s.whatsapp.net","fromMe":false,"id":"ACD85EDD1313D630F4089E685554606C","participant":"","addressingMode":"pn"},"messageTimestamp":1770014053},{"key":{"remoteJid":"6283841580448@s.whatsapp.net","fromMe":false,"id":"AC57749A6F2E74C9C779A8C83F9BF4CA","participant":"","addressingMode":"pn"},"messageTimestamp":1770014075}],"nextPreKeyId":813,"firstUnuploadedPreKeyId":813,"accountSyncCounter":1,"accountSettings":{"unarchiveChats":false},"registered":false,"account":{"details":"CLTZ270FEIOJgcwGGBogACgA","accountSignatureKey":"xUQ/Qe+GP1I1Twe8l2vHT9mNzjl2AiQW3i07WV8BPnw=","accountSignature":"lpvsUV39ghbpkBQgjLqSrAppvD6ZxZ4P37QWpUQyA40jHSJx4DgJnzcUsG0UgBXBJRyKM3z+qni5s7QTolRcBw==","deviceSignature":"ZHPUObgrJRcRygNFf1PL2cqoxAjNaaDVtkiMLYB1ACiOJfEIEOtJAcE8qFlHXRHoHVeFxb5t4fVQx/LuOgahjQ=="},"me":{"id":"6283841580448:59@s.whatsapp.net","lid":"196679806484724:59@lid","name":"AlifianN"},"signalIdentities":[{"identifier":{"name":"196679806484724:59@lid","deviceId":0},"identifierKey":{"type":"Buffer","data":"BcVEP0Hvhj9SNU8HvJdrx0/Zjc45dgIkFt4tO1lfAT58"}}],"platform":"android","routingInfo":{"type":"Buffer","data":"CAUIDQgC"},"lastAccountSyncTimestamp":1770013832,"lastPropHash":"3R9Z39","myAppStateKeyId":"AAAAAJLq"}